streamlit_carousel/__init__.py
streamlit_carousel/carousel/build/asset-manifest.json
streamlit_carousel/carousel/build/index.html
streamlit_carousel/carousel/build/static/css/main.d221dc40.css
streamlit_carousel/carousel/build/static/css/main.d221dc40.css.map
streamlit_carousel/carousel/build/static/js/main.31be8a25.js
streamlit_carousel/carousel/build/static/js/main.31be8a25.js.LICENSE.txt
streamlit_carousel/carousel/build/static/js/main.31be8a25.js.map
streamlit_carousel-1.1.1.dist-info/LICENSE
streamlit_carousel-1.1.1.dist-info/METADATA
streamlit_carousel-1.1.1.dist-info/WHEEL
streamlit_carousel-1.1.1.dist-info/entry_points.txt
streamlit_carousel-1.1.1.dist-info/top_level.txt
streamlit_carousel-1.1.1.dist-info/RECORD
